.gitignore
.style.yapf
piedventure/__init__.py
piedventure/__main_.py
piedventure/adventure.py
piedventure/art/bigfinish.ben
piedventure/art/supper.ben
piedventure/art/titleart.ben
piedventure/lib.py
piedventure/logic/leverlogic.ben
piedventure/rooms/__init__.py
piedventure/rooms/bigroom.py
piedventure/rooms/brown.py
piedventure/rooms/endroom.py
piedventure/rooms/gameroom.py
piedventure/rooms/green.py
piedventure/rooms/grue.py
piedventure/rooms/kroo.py
piedventure/rooms/kroo2.py
piedventure/rooms/mainroom.py
piedventure/rooms/red.py
piedventure/rooms/start.py
piedventure/rooms/white.py
piedventure/script/opening.ben
ruff.toml
piedventure-1.0.1.dist-info/entry_points.txt
piedventure-1.0.1.dist-info/LICENSE
piedventure-1.0.1.dist-info/METADATA
piedventure-1.0.1.dist-info/WHEEL
piedventure-1.0.1.dist-info/RECORD
