Metadata-Version: 2.1
Name: piedventure
Version: 1.0.1
Summary: Python port of BashVenture - Adventure for Bash
Home-page: https://github.com/rbscholtus/piedventure
License: MIT
Author: Barend Scholtus
Author-email: barend.scholtus@gmail.com
Requires-Python: >=3.9,<4.0
Classifier: Development Status :: 5 - Production/Stable
Classifier: Environment :: Console
Classifier: License :: OSI Approved :: MIT License
Classifier: Programming Language :: Python :: 3
Classifier: Programming Language :: Python :: 3.9
Classifier: Programming Language :: Python :: 3.10
Classifier: Programming Language :: Python :: 3.11
Classifier: Programming Language :: Python :: 3.12
Classifier: Topic :: Games/Entertainment
Project-URL: Repository, https://github.com/rbscholtus/piedventure
